.gitignore
.travis.yml
CHANGES.rst
MANIFEST.in
Makefile
README.rst
kitconcept.png
requirements.txt
setup.cfg
setup.py
tox.ini
ReactLibrary/__init__.py
docs/index.html
robotframework_react.egg-info/PKG-INFO
robotframework_react.egg-info/SOURCES.txt
robotframework_react.egg-info/dependency_links.txt
robotframework_react.egg-info/entry_points.txt
robotframework_react.egg-info/not-zip-safe
robotframework_react.egg-info/requires.txt
robotframework_react.egg-info/top_level.txt