Metadata-Version: 1.1
Name: robotframework-react
Version: 1.0.0a1
Summary: A Robot Framework library for React.
Home-page: https://kitconcept.com
Author: Timo Stollenwerk & David Rodriguez Fuentes
Author-email: stollenwerk@kitconcept.com
License: Apache License 2.0
Keywords: robotframework react javascript
Platform: UNKNOWN
Classifier: Development Status :: 3 - Alpha
Classifier: License :: OSI Approved :: Apache Software License
Classifier: Environment :: Web Environment
Classifier: Framework :: Robot Framework
Classifier: Programming Language :: Python :: 2.7
Classifier: Programming Language :: Python :: 3.5
Classifier: Programming Language :: Python :: Implementation :: CPython
